christophorus/__init__.py
christophorus/logger.py
splogging/__init__.py
splogging/logger.py
splogging/py.typed
splogging-0.0.5.dist-info/METADATA
splogging-0.0.5.dist-info/WHEEL
splogging-0.0.5.dist-info/top_level.txt
splogging-0.0.5.dist-info/RECORD
