Metadata-Version: 2.1
Name: splogging
Version: 0.0.5
Summary: Ease the creation of a logger
Home-page: https://github.com/steviepy/splogging
Author: Stevie Py
Author-email: st3v13py@gmail.com
License: UNKNOWN
Platform: UNKNOWN
Classifier: Programming Language :: Python :: 3
Classifier: License :: OSI Approved :: MIT License
Classifier: Operating System :: OS Independent
